cyz020403/__init__.py
cyz020403/test.py
cyz020403-0.0.4.dist-info/METADATA
cyz020403-0.0.4.dist-info/WHEEL
cyz020403-0.0.4.dist-info/top_level.txt
cyz020403-0.0.4.dist-info/RECORD
